pyufunc/__init.py
pyufunc/__init__.py
pyufunc/pkg_configs.py
pyufunc/util_ai/__init__.py
pyufunc/util_ai/_error_measurement.py
pyufunc/util_ai/_open_cv.py
pyufunc/util_ai/_pytorch.py
pyufunc/util_ai/_scikitlearn.py
pyufunc/util_ai/_scipy.py
pyufunc/util_ai/_tensorflow.py
pyufunc/util_algorithm/__init__.py
pyufunc/util_algorithm/_sort.py
pyufunc/util_dababase/__init__.py
pyufunc/util_data_processing/__init__.py
pyufunc/util_data_processing/_data_cleaning.py
pyufunc/util_data_processing/_dataclass.py
pyufunc/util_data_processing/_dict.py
pyufunc/util_data_processing/_float.py
pyufunc/util_data_processing/_int_to_alpha.py
pyufunc/util_data_processing/_list.py
pyufunc/util_data_processing/_str.py
pyufunc/util_datetime/__init__.py
pyufunc/util_datetime/_dt_format.py
pyufunc/util_datetime/_dt_group.py
pyufunc/util_datetime/_dt_time_difference.py
pyufunc/util_datetime/_dt_timezone.py
pyufunc/util_fullstack/__init__.py
pyufunc/util_fullstack/_database.py
pyufunc/util_fullstack/_django.py
pyufunc/util_fullstack/_django_restapi.py
pyufunc/util_fullstack/_fastapi.py
pyufunc/util_fullstack/_flask.py
pyufunc/util_geo/__init__.py
pyufunc/util_geo/_coordinate_convert.py
pyufunc/util_geo/_geo_area.py
pyufunc/util_geo/_geo_circle.py
pyufunc/util_geo/_geo_distance.py
pyufunc/util_geo/_geo_overture_map.py
pyufunc/util_geo/_geo_tif.py
pyufunc/util_geo/_get_osm_data.py
pyufunc/util_geo/_get_osm_place.py
pyufunc/util_geo/_gmns.py
pyufunc/util_geo/_shortest_path.py
pyufunc/util_git_pypi/__init__.py
pyufunc/util_git_pypi/_github.py
pyufunc/util_git_pypi/_gitlab.py
pyufunc/util_git_pypi/_pypi.py
pyufunc/util_git_pypi/static/__init__.py
pyufunc/util_git_pypi/static/user-agent-strings.json
pyufunc/util_gui/__init__.py
pyufunc/util_img/__init__.py
pyufunc/util_img/_img_cvt.py
pyufunc/util_img/_img_operate.py
pyufunc/util_log/__init__.py
pyufunc/util_log/_lg_datetime.py
pyufunc/util_log/_lg_logger.py
pyufunc/util_log/_lg_rotate_file_writer.py
pyufunc/util_log/_lg_stream.py
pyufunc-0.4.1.dist-info/METADATA
pyufunc-0.4.1.dist-info/WHEEL
pyufunc-0.4.1.dist-info/top_level.txt
pyufunc-0.4.1.dist-info/RECORD
