Metadata-Version: 2.4
Name: pyufunc
Version: 0.4.1
Summary: pyufunc consolidates frequently used utility functions into one cohesive package
Home-page: https://github.com/xyluo25/pyufunc
Author: Xiangyong Luo
Author-email: Xiangyong Luo <luoxiangyong01@gmail.com>, Xuesong Simon Zhou <xzhou74@asu.com>
Maintainer-email: Xiangyong Luo <luoxiangyong01@gmail.com>
License: MIT License
Project-URL: Homepage, https://github.com/xyluo25/pyufunc
Project-URL: Bug Tracker, https://github.com/xyluo25/pyufunc/issues
Project-URL: License, https://github.com/xyluo25/pyufunc/blob/main/LICENSE
Project-URL: Contact, https://github.com/xyluo25
Keywords: pyufunc,utility functions,utility-library,python-utilities,python-utils,utility,functions,common functions,common utility functions
Platform: all
Classifier: Programming Language :: Python :: 3
Classifier: Programming Language :: Python :: 3.10
Classifier: Programming Language :: Python :: 3.11
Classifier: Programming Language :: Python :: 3.12
Classifier: Programming Language :: Python :: 3.13
Classifier: License :: OSI Approved :: MIT License
Classifier: Intended Audience :: Developers
Classifier: Operating System :: OS Independent
Classifier: Topic :: Software Development :: Libraries
Requires-Python: >=3.10
Requires-Dist: pandas>=2.2.0
Dynamic: author
Dynamic: home-page
Dynamic: platform
Dynamic: requires-python
